AnsiList.py
ChorusFruit.py
Input.py
setup.py
ChorusFruit-0.1.5.dist-info/LICENCE
ChorusFruit-0.1.5.dist-info/METADATA
ChorusFruit-0.1.5.dist-info/WHEEL
ChorusFruit-0.1.5.dist-info/top_level.txt
ChorusFruit-0.1.5.dist-info/RECORD
