Metadata-Version: 2.1
Name: ChorusFruit
Version: 0.1.5
Summary: This module is a replacement for curses module
Author-email: "mani.f" <author@example.com>
Project-URL: Homepage, https://github.com/manifarizi/ChorusFruit
Project-URL: Bug Tracker, https://github.com/manifarizi/ChorusFruit/issues
Classifier: Programming Language :: Python :: 3
Classifier: License :: OSI Approved :: MIT License
Classifier: Operating System :: OS Independent
Requires-Python: >=3.7
License-File: LICENCE
